odoo/addons/stock_available_to_promise_release/README.rst
odoo/addons/stock_available_to_promise_release/__init__.py
odoo/addons/stock_available_to_promise_release/__manifest__.py
odoo/addons/stock_available_to_promise_release/i18n/es_AR.po
odoo/addons/stock_available_to_promise_release/i18n/stock_available_to_promise_release.pot
odoo/addons/stock_available_to_promise_release/models/__init__.py
odoo/addons/stock_available_to_promise_release/models/product_product.py
odoo/addons/stock_available_to_promise_release/models/res_company.py
odoo/addons/stock_available_to_promise_release/models/res_config_settings.py
odoo/addons/stock_available_to_promise_release/models/stock_location_route.py
odoo/addons/stock_available_to_promise_release/models/stock_move.py
odoo/addons/stock_available_to_promise_release/models/stock_picking.py
odoo/addons/stock_available_to_promise_release/models/stock_picking_type.py
odoo/addons/stock_available_to_promise_release/models/stock_rule.py
odoo/addons/stock_available_to_promise_release/readme/CONFIGURE.rst
odoo/addons/stock_available_to_promise_release/readme/CONTRIBUTORS.rst
odoo/addons/stock_available_to_promise_release/readme/DESCRIPTION.rst
odoo/addons/stock_available_to_promise_release/readme/USAGE.rst
odoo/addons/stock_available_to_promise_release/static/description/icon.png
odoo/addons/stock_available_to_promise_release/static/description/index.html
odoo/addons/stock_available_to_promise_release/tests/__init__.py
odoo/addons/stock_available_to_promise_release/tests/common.py
odoo/addons/stock_available_to_promise_release/tests/test_reservation.py
odoo/addons/stock_available_to_promise_release/views/product_product_views.xml
odoo/addons/stock_available_to_promise_release/views/res_config_settings.xml
odoo/addons/stock_available_to_promise_release/views/stock_location_route_views.xml
odoo/addons/stock_available_to_promise_release/views/stock_move_views.xml
odoo/addons/stock_available_to_promise_release/views/stock_picking_type_views.xml
odoo13_addon_stock_available_to_promise_release-13.0.1.11.1.dist-info/METADATA
odoo13_addon_stock_available_to_promise_release-13.0.1.11.1.dist-info/WHEEL
odoo13_addon_stock_available_to_promise_release-13.0.1.11.1.dist-info/top_level.txt
odoo13_addon_stock_available_to_promise_release-13.0.1.11.1.dist-info/RECORD
