Metadata-Version: 2.1
Name: odoo13-addon-stock-available-to-promise-release
Version: 13.0.1.11.1
Summary: Release Operations based on available to promise
Home-page: https://github.com/OCA/wms
Author: Camptocamp,Odoo Community Association (OCA)
Author-email: support@odoo-community.org
License: LGPL-3
Platform: UNKNOWN
Classifier: Programming Language :: Python
Classifier: Framework :: Odoo
Classifier: License :: OSI Approved :: GNU Lesser General Public License v3 (LGPLv3)
Classifier: Development Status :: 3 - Alpha
Requires-Python: >=3.5
Requires-Dist: odoo (<13.1dev,>=13.0a)
